todo_cli_tddschn/__init__.py
todo_cli_tddschn/app.py
todo_cli_tddschn/cli.py
todo_cli_tddschn/config.py
todo_cli_tddschn/database.py
todo_cli_tddschn/info_commands.py
todo_cli_tddschn/list_commands.py
todo_cli_tddschn/models.py
todo_cli_tddschn/todo_repl.py
todo_cli_tddschn/todo_shell.py
todo_cli_tddschn/utils.py
todo_cli_tddschn/utils_commands.py
todo_cli_tddschn-2.0.7.dist-info/entry_points.txt
todo_cli_tddschn-2.0.7.dist-info/LICENSE
todo_cli_tddschn-2.0.7.dist-info/WHEEL
todo_cli_tddschn-2.0.7.dist-info/METADATA
todo_cli_tddschn-2.0.7.dist-info/RECORD
