Metadata-Version: 2.1
Name: todo-cli-tddschn
Version: 2.0.7
Summary: CLI Todo app made with typer, sqlite and a REST API
Home-page: https://github.com/tddschn/todo-cli-tddschn
License: MIT
Keywords: todo,cli,sqlite,typer,fastapi,rest
Author: Xinyuan Chen
Author-email: 45612704+tddschn@users.noreply.github.com
Requires-Python: >=3.10,<3.11
Classifier: License :: OSI Approved :: MIT License
Classifier: Programming Language :: Python :: 3
Classifier: Programming Language :: Python :: 3.10
Requires-Dist: PyYAML (>=6.0,<7.0)
Requires-Dist: colorama (==0.4.4)
Requires-Dist: fastapi[api] (>=0.75.2,<0.76.0)
Requires-Dist: logging-utils-tddschn (>=0.1.10,<0.2.0)
Requires-Dist: prompt-toolkit (>=3.0.29,<4.0.0)
Requires-Dist: shellingham (==1.4.0)
Requires-Dist: sqlmodel (>=0.0.6,<0.0.7)
Requires-Dist: tabulate (>=0.8.9,<0.9.0)
Requires-Dist: typer (>=0.4.1,<0.5.0)
Requires-Dist: uvicorn[api] (>=0.17.6,<0.18.0)
Project-URL: Bug Tracker, https://github.com/tddschn/todo-cli-tddschn/issues
Project-URL: Repository, https://github.com/tddschn/todo-cli-tddschn
